README.rst
setup.cfg
setup.py
beret/__init__.py
beret/beret.py
beret.egg-info/PKG-INFO
beret.egg-info/SOURCES.txt
beret.egg-info/dependency_links.txt
beret.egg-info/requires.txt
beret.egg-info/top_level.txt
bin/beret