Metadata-Version: 1.0
Name: beret
Version: 0.2.2
Summary: Parse a csv file and score through a yhat model
Home-page: https://github.com/yhat/beret
Author: Eric Chiang
Author-email: info@yhathq.com
License: BSD
Platform: UNKNOWN
